odoo/addons/ssi_account_receivable_penalty_sale/README.rst
odoo/addons/ssi_account_receivable_penalty_sale/__init__.py
odoo/addons/ssi_account_receivable_penalty_sale/__manifest__.py
odoo/addons/ssi_account_receivable_penalty_sale/data/policy_template_data.xml
odoo/addons/ssi_account_receivable_penalty_sale/i18n/ssi_account_receivable_penalty_sale.pot
odoo/addons/ssi_account_receivable_penalty_sale/models/__init__.py
odoo/addons/ssi_account_receivable_penalty_sale/models/sale_order.py
odoo/addons/ssi_account_receivable_penalty_sale/static/description/icon.png
odoo/addons/ssi_account_receivable_penalty_sale/views/sale_order_views.xml
odoo14_addon_ssi_account_receivable_penalty_sale-14.0.1.2.0.dist-info/METADATA
odoo14_addon_ssi_account_receivable_penalty_sale-14.0.1.2.0.dist-info/WHEEL
odoo14_addon_ssi_account_receivable_penalty_sale-14.0.1.2.0.dist-info/top_level.txt
odoo14_addon_ssi_account_receivable_penalty_sale-14.0.1.2.0.dist-info/RECORD
